deppy/.DS_Store
deppy/__init__.py
deppy/decorator.py
deppy/di.py
deppy/registry.py
deppy/scope.py
deppy/type.py
deppy/util.py
deppy-0.0.0.dist-info/LICENSE
deppy-0.0.0.dist-info/WHEEL
deppy-0.0.0.dist-info/METADATA
deppy-0.0.0.dist-info/RECORD
